mgsub/models.py
mgsub/_version.py
mgsub/__init__.py
mgsub/forms.py
mgsub/admin.py
mgsub/mailgun.py
mgsub/tests.py
mgsub/urls.py
mgsub/views.py
mgsub/templates/mgsub/thanks.html
mgsub/templates/mgsub/welcome.txt
mgsub/templates/mgsub/signup.html
django_mgsub-0.2.0.dist-info/RECORD
django_mgsub-0.2.0.dist-info/metadata.json
django_mgsub-0.2.0.dist-info/WHEEL
django_mgsub-0.2.0.dist-info/DESCRIPTION.rst
django_mgsub-0.2.0.dist-info/top_level.txt
django_mgsub-0.2.0.dist-info/METADATA
