Metadata-Version: 2.0
Name: django-mgsub
Version: 0.2.0
Summary: Subscribe Mailgun mailing lists from Django
Home-page: https://github.com/ferrix/mgsub/
Author: Ferrix Hovi
Author-email: ferrix+pypi@ferrix.fi
License: MIT License
Platform: UNKNOWN
Classifier: Environment :: Web Environment
Classifier: Framework :: Django
Classifier: Framework :: Django :: 1.8
Classifier: Intended Audience :: Developers
Classifier: Operating System :: OS Independent
Classifier: Programming Language :: Python
Classifier: License :: OSI Approved :: MIT License
Classifier: Topic :: Internet :: WWW/HTTP
Classifier: Topic :: Internet :: WWW/HTTP :: Dynamic Content
Requires-Dist: certifi (==2018.11.29)
Requires-Dist: requests (==2.21.0)
